threatxmanager/__init__.py
threatxmanager/cli.py
threatxmanager/base_module/__init__.py
threatxmanager/base_module/base_module.py
threatxmanager/base_module/strix_serveses.py
threatxmanager/config/__init__.py
threatxmanager/config/manager_config.py
threatxmanager/dbmanager/__init__.py
threatxmanager/dbmanager/connection.py
threatxmanager/dbmanager/models.py
threatxmanager/dbmanager/modules_models/__init__.py
threatxmanager/dbmanager/modules_models/certificate_model.py
threatxmanager/dbmanager/modules_models/cper_model.py
threatxmanager/dbmanager/modules_models/stix_objects.py
threatxmanager/dbmanager/modules_models/vendas.py
threatxmanager/logmanager/__init__.py
threatxmanager/logmanager/logmanager.py
threatxmanager/modules/__init__.py
threatxmanager/modules/external/__init__.py
threatxmanager/modules/external/cpe_connector_module.py
threatxmanager/modules/external/crtsh_connector_module.py
threatxmanager/modules/external/my_module.py
threatxmanager/modules/external/my_module_db.py
threatxmanager-0.2.0.dist-info/METADATA
threatxmanager-0.2.0.dist-info/WHEEL
threatxmanager-0.2.0.dist-info/entry_points.txt
threatxmanager-0.2.0.dist-info/top_level.txt
threatxmanager-0.2.0.dist-info/RECORD
