Metadata-Version: 2.2
Name: threatxmanager
Version: 0.2.0
Summary: Manager database threat Intelligence
Author-email: Luiz Correa <zcorrea357@gmail.com>
Project-URL: homepage, https://github.com/CorreaCyberLabsLTD/threatXmanager
Project-URL: source, https://github.com/CorreaCyberLabsLTD/threatXmanager
Project-URL: changelog, https://github.com/CorreaCyberLabsLTD/threatXmanager/blob/main/CHANGELOG.md
Project-URL: releasenotes, https://github.com/CorreaCyberLabsLTD/threatXmanager/releases
Project-URL: documentation, https://github.com/CorreaCyberLabsLTD/threatXmanager
Project-URL: issues, https://github.com/CorreaCyberLabsLTD/threatXmanager/issues
Requires-Python: <4.0,>=3.10
Requires-Dist: httpx>=0.28.1
Requires-Dist: langcodes>=3.5.0
Requires-Dist: loguru>=0.7.3
Requires-Dist: mariadb>=1.1.12
Requires-Dist: opensearch-py>=2.8.0
Requires-Dist: prompt-toolkit>=3.0.50
Requires-Dist: psycopg2>=2.9.10
Requires-Dist: pydantic>=2.10.6
Requires-Dist: pymysql>=1.1.1
Requires-Dist: pytz>=2025.1
Requires-Dist: requests>=2.32.3
Requires-Dist: sentry-sdk>=2.22.0
Requires-Dist: sqlalchemy>=2.0.39
Requires-Dist: stix2>=3.0.1
Requires-Dist: toml>=0.10.2
Requires-Dist: tweepy>=4.15.0
Requires-Dist: typer>=0.15.1
Requires-Dist: validators>=0.34.0
